parquet_lf/__init__.py
parquet_lf/cli.py
parquet_lf/info.py
parquet_lf/main.py
parquet_lf/command/__init__.py
parquet_lf/command/from_parquet_csv.py
parquet_lf/command/from_parquet_ndjson.py
parquet_lf/command/info.py
parquet_lf/command/to_parquet_csv.py
parquet_lf/command/to_parquet_ndjson.py
parquet_lf/converters/__init__.py
parquet_lf/converters/base.py
parquet_lf/converters/csv.py
parquet_lf/converters/ndjson.py
parquet_lf-1.0.0.dist-info/METADATA
parquet_lf-1.0.0.dist-info/WHEEL
parquet_lf-1.0.0.dist-info/entry_points.txt
parquet_lf-1.0.0.dist-info/licenses/LICENSE
parquet_lf-1.0.0.dist-info/RECORD
