Metadata-Version: 2.4
Name: parquet-lf
Version: 1.0.0
Summary: A lingua franca utility for converting between data formats (JSON, CSV) and Parquet.
Project-URL: Homepage, https://github.com/mattjmcnaughton/parquet-lf
Project-URL: Repository, https://github.com/mattjmcnaughton/parquet-lf
Project-URL: Issues, https://github.com/mattjmcnaughton/parquet-lf/issues
Author: Matt McNaughton
License-Expression: MIT
License-File: LICENSE
Keywords: cli,conversion,csv,data,json,parquet
Classifier: Development Status :: 3 - Alpha
Classifier: Environment :: Console
Classifier: Intended Audience :: Developers
Classifier: License :: OSI Approved :: MIT License
Classifier: Operating System :: OS Independent
Classifier: Programming Language :: Python :: 3
Classifier: Programming Language :: Python :: 3.13
Classifier: Topic :: File Formats
Classifier: Topic :: Utilities
Requires-Python: >=3.13
Requires-Dist: polars>=1.36.1
Requires-Dist: structlog>=25.4.0
Requires-Dist: typer>=0.17.4
